xontrib/fish_completer.py
xontrib_fish_completer-0.0.1.dist-info/LICENSE
xontrib_fish_completer-0.0.1.dist-info/METADATA
xontrib_fish_completer-0.0.1.dist-info/WHEEL
xontrib_fish_completer-0.0.1.dist-info/top_level.txt
xontrib_fish_completer-0.0.1.dist-info/RECORD
